{
  "Data": [
    {
      "BowlerID": 54,
      "BowlerName": "Bacon, Whitney",
      "TeamID": 5,
      "TeamName": "Barely Bowling",
      "AverageBeforeBowling": 132,
      "HandicapBeforeBowling": 79,
      "GameNum1": 1,
      "ScoreType1": "S",
      "Score1": 109,
      "GameNum2": 2,
      "ScoreType2": "S",
      "Score2": 124,
      "GameNum3": 0,
      "ScoreType3": "0",
      "Score3": 0,
      "GameNum4": 0,
      "ScoreType4": "0",
      "Score4": 0,
      "GameNum5": 0,
      "ScoreType5": "0",
      "Score5": 0,
      "GameNum6": 0,
      "ScoreType6": "0",
      "Score6": 0,
      "SeriesTotal": 233,
      "HandicapSeriesTotal": 391,
      "PlusMinusAverage": -16,
      "TeamNum": 5
    },
    {
      "BowlerID": 46,
      "BowlerName": "Bell, Tracy",
      "TeamID": 1,
      "TeamName": "One More",
      "AverageBeforeBowling": 224,
      "HandicapBeforeBowling": 0,
      "GameNum1": 1,
      "ScoreType1": "S",
      "Score1": 211,
      "GameNum2": 2,
      "ScoreType2": "S",
      "Score2": 227,
      "GameNum3": 0,
      "ScoreType3": "0",
      "Score3": 0,
      "GameNum4": 0,
      "ScoreType4": "0",
      "Score4": 0,
      "GameNum5": 0,
      "ScoreType5": "0",
      "Score5": 0,
      "GameNum6": 0,
      "ScoreType6": "0",
      "Score6": 0,
      "SeriesTotal": 438,
      "HandicapSeriesTotal": 438,
      "PlusMinusAverage": -5,
      "TeamNum": 1
    },
    {
      "BowlerID": 107,
      "BowlerName": "Boeding, Chris",
      "TeamID": 11,
      "TeamName": "Guess Who",
      "AverageBeforeBowling": 166,
      "HandicapBeforeBowling": 48,
      "GameNum1": 1,
      "ScoreType1": "S",
      "Score1": 162,
      "GameNum2": 2,
      "ScoreType2": "S",
      "Score2": 119,
      "GameNum3": 0,
      "ScoreType3": "0",
      "Score3": 0,
      "GameNum4": 0,
      "ScoreType4": "0",
      "Score4": 0,
      "GameNum5": 0,
      "ScoreType5": "0",
      "Score5": 0,
      "GameNum6": 0,
      "ScoreType6": "0",
      "Score6": 0,
      "SeriesTotal": 281,
      "HandicapSeriesTotal": 377,
      "PlusMinusAverage": -26,
      "TeamNum": 11
    },
    {
      "BowlerID": 82,
      "BowlerName": "Burkhardt, Drew",
      "TeamID": 15,
      "TeamName": "XXX Dancers",
      "AverageBeforeBowling": 172,
      "HandicapBeforeBowling": 43,
      "GameNum1": 1,
      "ScoreType1": "S",
      "Score1": 186,
      "GameNum2": 2,
      "ScoreType2": "S",
      "Score2": 146,
      "GameNum3": 0,
      "ScoreType3": "0",
      "Score3": 0,
      "GameNum4": 0,
      "ScoreType4": "0",
      "Score4": 0,
      "GameNum5": 0,
      "ScoreType5": "0",
      "Score5": 0,
      "GameNum6": 0,
      "ScoreType6": "0",
      "Score6": 0,
      "SeriesTotal": 332,
      "HandicapSeriesTotal": 418,
      "PlusMinusAverage": -6,
      "TeamNum": 15
    },
    {
      "BowlerID": 28,
      "BowlerName": "B, B",
      "TeamID": 23,
      "TeamName": "Split Happens",
      "AverageBeforeBowling": 175,
      "HandicapBeforeBowling": 40,
      "GameNum1": 1,
      "ScoreType1": "S",
      "Score1": 159,
      "GameNum2": 2,
      "ScoreType2": "S",
      "Score2": 181,
      "GameNum3": 0,
      "ScoreType3": "0",
      "Score3": 0,
      "GameNum4": 0,
      "ScoreType4": "0",
      "Score4": 0,
      "GameNum5": 0,
      "ScoreType5": "0",
      "Score5": 0,
      "GameNum6": 0,
      "ScoreType6": "0",
      "Score6": 0,
      "SeriesTotal": 340,
      "HandicapSeriesTotal": 420,
      "PlusMinusAverage": -5,
      "TeamNum": 23
    },
    {
      "BowlerID": 56,
      "BowlerName": "Chandler, Cory",
      "TeamID": 9,
      "TeamName": "Bob_Rossing It",
      "AverageBeforeBowling": 155,
      "HandicapBeforeBowling": 58,
      "GameNum1": 1,
      "ScoreType1": "S",
      "Score1": 136,
      "GameNum2": 2,
      "ScoreType2": "S",
      "Score2": 174,
      "GameNum3": 0,
      "ScoreType3": "0",
      "Score3": 0,
      "GameNum4": 0,
      "ScoreType4": "0",
      "Score4": 0,
      "GameNum5": 0,
      "ScoreType5": "0",
      "Score5": 0,
      "GameNum6": 0,
      "ScoreType6": "0",
      "Score6": 0,
      "SeriesTotal": 310,
      "HandicapSeriesTotal": 426,
      "PlusMinusAverage": 0,
      "TeamNum": 9
    },
    {
      "BowlerID": 41,
      "BowlerName": "Cray, Jason",
      "TeamID": 21,
      "TeamName": "AWACS ON/OFF",
      "AverageBeforeBowling": 202,
      "HandicapBeforeBowling": 16,
      "GameNum1": 1,
      "ScoreType1": "S",
      "Score1": 183,
      "GameNum2": 2,
      "ScoreType2": "S",
      "Score2": 236,
      "GameNum3": 0,
      "ScoreType3": "0",
      "Score3": 0,
      "GameNum4": 0,
      "ScoreType4": "0",
      "Score4": 0,
      "GameNum5": 0,
      "ScoreType5": "0",
      "Score5": 0,
      "GameNum6": 0,
      "ScoreType6": "0",
      "Score6": 0,
      "SeriesTotal": 419,
      "HandicapSeriesTotal": 451,
      "PlusMinusAverage": 7,
      "TeamNum": 21
    },
    {
      "BowlerID": 9,
      "BowlerName": "Crooks, Neal",
      "TeamID": 22,
      "TeamName": "We Don't Give A Split",
      "AverageBeforeBowling": 119,
      "HandicapBeforeBowling": 90,
      "GameNum1": 1,
      "ScoreType1": "S",
      "Score1": 125,
      "GameNum2": 2,
      "ScoreType2": "S",
      "Score2": 122,
      "GameNum3": 0,
      "ScoreType3": "0",
      "Score3": 0,
      "GameNum4": 0,
      "ScoreType4": "0",
      "Score4": 0,
      "GameNum5": 0,
      "ScoreType5": "0",
      "Score5": 0,
      "GameNum6": 0,
      "ScoreType6": "0",
      "Score6": 0,
      "SeriesTotal": 247,
      "HandicapSeriesTotal": 427,
      "PlusMinusAverage": 4,
      "TeamNum": 22
    },
    {
      "BowlerID": 122,
      "BowlerName": "Curry, Lonny",
      "TeamID": 26,
      "TeamName": "Top Gun",
      "AverageBeforeBowling": 157,
      "HandicapBeforeBowling": 56,
      "GameNum1": 1,
      "ScoreType1": "S",
      "Score1": 154,
      "GameNum2": 2,
      "ScoreType2": "S",
      "Score2": 161,
      "GameNum3": 0,
      "ScoreType3": "0",
      "Score3": 0,
      "GameNum4": 0,
      "ScoreType4": "0",
      "Score4": 0,
      "GameNum5": 0,
      "ScoreType5": "0",
      "Score5": 0,
      "GameNum6": 0,
      "ScoreType6": "0",
      "Score6": 0,
      "SeriesTotal": 315,
      "HandicapSeriesTotal": 427,
      "PlusMinusAverage": 0,
      "TeamNum": 26
    },
    {
      "BowlerID": 30,
      "BowlerName": "Dalbol, Andrew",
      "TeamID": 24,
      "TeamName": "Mark it Zero !",
      "AverageBeforeBowling": 192,
      "HandicapBeforeBowling": 25,
      "GameNum1": 1,
      "ScoreType1": "S",
      "Score1": 182,
      "GameNum2": 2,
      "ScoreType2": "S",
      "Score2": 200,
      "GameNum3": 0,
      "ScoreType3": "0",
      "Score3": 0,
      "GameNum4": 0,
      "ScoreType4": "0",
      "Score4": 0,
      "GameNum5": 0,
      "ScoreType5": "0",
      "Score5": 0,
      "GameNum6": 0,
      "ScoreType6": "0",
      "Score6": 0,
      "SeriesTotal": 382,
      "HandicapSeriesTotal": 432,
      "PlusMinusAverage": -1,
      "TeamNum": 24
    },
    {
      "BowlerID": 131,
      "BowlerName": "Defields, Jaden",
      "TeamID": 27,
      "TeamName": "The Century Club",
      "AverageBeforeBowling": 165,
      "HandicapBeforeBowling": 49,
      "GameNum1": 1,
      "ScoreType1": "S",
      "Score1": 166,
      "GameNum2": 2,
      "ScoreType2": "S",
      "Score2": 159,
      "GameNum3": 0,
      "ScoreType3": "0",
      "Score3": 0,
      "GameNum4": 0,
      "ScoreType4": "0",
      "Score4": 0,
      "GameNum5": 0,
      "ScoreType5": "0",
      "Score5": 0,
      "GameNum6": 0,
      "ScoreType6": "0",
      "Score6": 0,
      "SeriesTotal": 325,
      "HandicapSeriesTotal": 423,
      "PlusMinusAverage": -3,
      "TeamNum": 27
    },
    {
      "BowlerID": 62,
      "BowlerName": "Degroot, Chris",
      "TeamID": 4,
      "TeamName": "Bad Attitude",
      "AverageBeforeBowling": 206,
      "HandicapBeforeBowling": 12,
      "GameNum1": 1,
      "ScoreType1": "S",
      "Score1": 169,
      "GameNum2": 2,
      "ScoreType2": "S",
      "Score2": 184,
      "GameNum3": 0,
      "ScoreType3": "0",
      "Score3": 0,
      "GameNum4": 0,
      "ScoreType4": "0",
      "Score4": 0,
      "GameNum5": 0,
      "ScoreType5": "0",
      "Score5": 0,
      "GameNum6": 0,
      "ScoreType6": "0",
      "Score6": 0,
      "SeriesTotal": 353,
      "HandicapSeriesTotal": 377,
      "PlusMinusAverage": -30,
      "TeamNum": 4
    },
    {
      "BowlerID": 8,
      "BowlerName": "D, M",
      "TeamID": 26,
      "TeamName": "Top Gun",
      "AverageBeforeBowling": 189,
      "HandicapBeforeBowling": 27,
      "GameNum1": 1,
      "ScoreType1": "S",
      "Score1": 181,
      "GameNum2": 2,
      "ScoreType2": "S",
      "Score2": 192,
      "GameNum3": 0,
      "ScoreType3": "0",
      "Score3": 0,
      "GameNum4": 0,
      "ScoreType4": "0",
      "Score4": 0,
      "GameNum5": 0,
      "ScoreType5": "0",
      "Score5": 0,
      "GameNum6": 0,
      "ScoreType6": "0",
      "Score6": 0,
      "SeriesTotal": 373,
      "HandicapSeriesTotal": 427,
      "PlusMinusAverage": -3,
      "TeamNum": 26
    },
    {
      "BowlerID": 33,
      "BowlerName": "Evenson, Rayce",
      "TeamID": 28,
      "TeamName": "Who gives a split",
      "AverageBeforeBowling": 113,
      "HandicapBeforeBowling": 96,
      "GameNum1": 1,
      "ScoreType1": "S",
      "Score1": 130,
      "GameNum2": 2,
      "ScoreType2": "S",
      "Score2": 133,
      "GameNum3": 0,
      "ScoreType3": "0",
      "Score3": 0,
      "GameNum4": 0,
      "ScoreType4": "0",
      "Score4": 0,
      "GameNum5": 0,
      "ScoreType5": "0",
      "Score5": 0,
      "GameNum6": 0,
      "ScoreType6": "0",
      "Score6": 0,
      "SeriesTotal": 263,
      "HandicapSeriesTotal": 455,
      "PlusMinusAverage": 18,
      "TeamNum": 28
    },
    {
      "BowlerID": 66,
      "BowlerName": "Gabrielson, John",
      "TeamID": 13,
      "TeamName": "Lane Violation",
      "AverageBeforeBowling": 206,
      "HandicapBeforeBowling": 12,
      "GameNum1": 1,
      "ScoreType1": "S",
      "Score1": 157,
      "GameNum2": 2,
      "ScoreType2": "S",
      "Score2": 181,
      "GameNum3": 0,
      "ScoreType3": "0",
      "Score3": 0,
      "GameNum4": 0,
      "ScoreType4": "0",
      "Score4": 0,
      "GameNum5": 0,
      "ScoreType5": "0",
      "Score5": 0,
      "GameNum6": 0,
      "ScoreType6": "0",
      "Score6": 0,
      "SeriesTotal": 338,
      "HandicapSeriesTotal": 362,
      "PlusMinusAverage": -37,
      "TeamNum": 13
    },
    {
      "BowlerID": 21,
      "BowlerName": "Geesaman, Bob",
      "TeamID": 1,
      "TeamName": "One More",
      "AverageBeforeBowling": 215,
      "HandicapBeforeBowling": 4,
      "GameNum1": 1,
      "ScoreType1": "S",
      "Score1": 202,
      "GameNum2": 2,
      "ScoreType2": "S",
      "Score2": 233,
      "GameNum3": 0,
      "ScoreType3": "0",
      "Score3": 0,
      "GameNum4": 0,
      "ScoreType4": "0",
      "Score4": 0,
      "GameNum5": 0,
      "ScoreType5": "0",
      "Score5": 0,
      "GameNum6": 0,
      "ScoreType6": "0",
      "Score6": 0,
      "SeriesTotal": 435,
      "HandicapSeriesTotal": 443,
      "PlusMinusAverage": 2,
      "TeamNum": 1
    },
    {
      "BowlerID": 49,
      "BowlerName": "Godfrey, Heidi",
      "TeamID": 2,
      "TeamName": "Alias Smith and Godfrey",
      "AverageBeforeBowling": 140,
      "HandicapBeforeBowling": 72,
      "GameNum1": 1,
      "ScoreType1": "S",
      "Score1": 109,
      "GameNum2": 2,
      "ScoreType2": "S",
      "Score2": 128,
      "GameNum3": 0,
      "ScoreType3": "0",
      "Score3": 0,
      "GameNum4": 0,
      "ScoreType4": "0",
      "Score4": 0,
      "GameNum5": 0,
      "ScoreType5": "0",
      "Score5": 0,
      "GameNum6": 0,
      "ScoreType6": "0",
      "Score6": 0,
      "SeriesTotal": 237,
      "HandicapSeriesTotal": 381,
      "PlusMinusAverage": -22,
      "TeamNum": 2
    },
    {
      "BowlerID": 3,
      "BowlerName": "G, M",
      "TeamID": 20,
      "TeamName": "SPAM",
      "AverageBeforeBowling": 178,
      "HandicapBeforeBowling": 37,
      "GameNum1": 1,
      "ScoreType1": "S",
      "Score1": 149,
      "GameNum2": 2,
      "ScoreType2": "S",
      "Score2": 160,
      "GameNum3": 0,
      "ScoreType3": "0",
      "Score3": 0,
      "GameNum4": 0,
      "ScoreType4": "0",
      "Score4": 0,
      "GameNum5": 0,
      "ScoreType5": "0",
      "Score5": 0,
      "GameNum6": 0,
      "ScoreType6": "0",
      "Score6": 0,
      "SeriesTotal": 309,
      "HandicapSeriesTotal": 383,
      "PlusMinusAverage": -24,
      "TeamNum": 20
    },
    {
      "BowlerID": 16,
      "BowlerName": "H, K",
      "TeamID": 10,
      "TeamName": "Engineering Strikes",
      "AverageBeforeBowling": 198,
      "HandicapBeforeBowling": 19,
      "GameNum1": 1,
      "ScoreType1": "S",
      "Score1": 246,
      "GameNum2": 2,
      "ScoreType2": "S",
      "Score2": 226,
      "GameNum3": 0,
      "ScoreType3": "0",
      "Score3": 0,
      "GameNum4": 0,
      "ScoreType4": "0",
      "Score4": 0,
      "GameNum5": 0,
      "ScoreType5": "0",
      "Score5": 0,
      "GameNum6": 0,
      "ScoreType6": "0",
      "Score6": 0,
      "SeriesTotal": 472,
      "HandicapSeriesTotal": 510,
      "PlusMinusAverage": 38,
      "TeamNum": 10
    },
    {
      "BowlerID": 67,
      "BowlerName": "Hecker, Allison",
      "TeamID": 13,
      "TeamName": "Lane Violation",
      "AverageBeforeBowling": 117,
      "HandicapBeforeBowling": 92,
      "GameNum1": 1,
      "ScoreType1": "S",
      "Score1": 139,
      "GameNum2": 2,
      "ScoreType2": "S",
      "Score2": 131,
      "GameNum3": 0,
      "ScoreType3": "0",
      "Score3": 0,
      "GameNum4": 0,
      "ScoreType4": "0",
      "Score4": 0,
      "GameNum5": 0,
      "ScoreType5": "0",
      "Score5": 0,
      "GameNum6": 0,
      "ScoreType6": "0",
      "Score6": 0,
      "SeriesTotal": 270,
      "HandicapSeriesTotal": 454,
      "PlusMinusAverage": 18,
      "TeamNum": 13
    },
    {
      "BowlerID": 80,
      "BowlerName": "Herbrand, Justin",
      "TeamID": 9,
      "TeamName": "Bob_Rossing It",
      "AverageBeforeBowling": 142,
      "HandicapBeforeBowling": 70,
      "GameNum1": 1,
      "ScoreType1": "S",
      "Score1": 113,
      "GameNum2": 2,
      "ScoreType2": "S",
      "Score2": 187,
      "GameNum3": 0,
      "ScoreType3": "0",
      "Score3": 0,
      "GameNum4": 0,
      "ScoreType4": "0",
      "Score4": 0,
      "GameNum5": 0,
      "ScoreType5": "0",
      "Score5": 0,
      "GameNum6": 0,
      "ScoreType6": "0",
      "Score6": 0,
      "SeriesTotal": 300,
      "HandicapSeriesTotal": 440,
      "PlusMinusAverage": 8,
      "TeamNum": 9
    },
    {
      "BowlerID": 89,
      "BowlerName": "K, D",
      "TeamID": 8,
      "TeamName": "Lunch Hour Hookers",
      "AverageBeforeBowling": 191,
      "HandicapBeforeBowling": 26,
      "GameNum1": 1,
      "ScoreType1": "S",
      "Score1": 194,
      "GameNum2": 2,
      "ScoreType2": "S",
      "Score2": 234,
      "GameNum3": 0,
      "ScoreType3": "0",
      "Score3": 0,
      "GameNum4": 0,
      "ScoreType4": "0",
      "Score4": 0,
      "GameNum5": 0,
      "ScoreType5": "0",
      "Score5": 0,
      "GameNum6": 0,
      "ScoreType6": "0",
      "Score6": 0,
      "SeriesTotal": 428,
      "HandicapSeriesTotal": 480,
      "PlusMinusAverage": 23,
      "TeamNum": 8
    },
    {
      "BowlerID": 132,
      "BowlerName": "Karlen, Jessica",
      "TeamID": 16,
      "TeamName": "The Munsons",
      "AverageBeforeBowling": 122,
      "HandicapBeforeBowling": 88,
      "GameNum1": 1,
      "ScoreType1": "S",
      "Score1": 99,
      "GameNum2": 2,
      "ScoreType2": "S",
      "Score2": 121,
      "GameNum3": 0,
      "ScoreType3": "0",
      "Score3": 0,
      "GameNum4": 0,
      "ScoreType4": "0",
      "Score4": 0,
      "GameNum5": 0,
      "ScoreType5": "0",
      "Score5": 0,
      "GameNum6": 0,
      "ScoreType6": "0",
      "Score6": 0,
      "SeriesTotal": 220,
      "HandicapSeriesTotal": 396,
      "PlusMinusAverage": -12,
      "TeamNum": 16
    },
    {
      "BowlerID": 133,
      "BowlerName": "Karlen, Matthew",
      "TeamID": 16,
      "TeamName": "The Munsons",
      "AverageBeforeBowling": 190,
      "HandicapBeforeBowling": 27,
      "GameNum1": 1,
      "ScoreType1": "S",
      "Score1": 205,
      "GameNum2": 2,
      "ScoreType2": "S",
      "Score2": 208,
      "GameNum3": 0,
      "ScoreType3": "0",
      "Score3": 0,
      "GameNum4": 0,
      "ScoreType4": "0",
      "Score4": 0,
      "GameNum5": 0,
      "ScoreType5": "0",
      "Score5": 0,
      "GameNum6": 0,
      "ScoreType6": "0",
      "Score6": 0,
      "SeriesTotal": 413,
      "HandicapSeriesTotal": 467,
      "PlusMinusAverage": 16,
      "TeamNum": 16
    },
    {
      "BowlerID": 45,
      "BowlerName": "K, K",
      "TeamID": 11,
      "TeamName": "Guess Who",
      "AverageBeforeBowling": 155,
      "HandicapBeforeBowling": 58,
      "GameNum1": 1,
      "ScoreType1": "S",
      "Score1": 132,
      "GameNum2": 2,
      "ScoreType2": "S",
      "Score2": 179,
      "GameNum3": 0,
      "ScoreType3": "0",
      "Score3": 0,
      "GameNum4": 0,
      "ScoreType4": "0",
      "Score4": 0,
      "GameNum5": 0,
      "ScoreType5": "0",
      "Score5": 0,
      "GameNum6": 0,
      "ScoreType6": "0",
      "Score6": 0,
      "SeriesTotal": 311,
      "HandicapSeriesTotal": 427,
      "PlusMinusAverage": 0,
      "TeamNum": 11
    },
    {
      "BowlerID": 118,
      "BowlerName": "Lampe, Jason",
      "TeamID": 12,
      "TeamName": "I am Root",
      "AverageBeforeBowling": 147,
      "HandicapBeforeBowling": 65,
      "GameNum1": 1,
      "ScoreType1": "S",
      "Score1": 171,
      "GameNum2": 2,
      "ScoreType2": "S",
      "Score2": 112,
      "GameNum3": 0,
      "ScoreType3": "0",
      "Score3": 0,
      "GameNum4": 0,
      "ScoreType4": "0",
      "Score4": 0,
      "GameNum5": 0,
      "ScoreType5": "0",
      "Score5": 0,
      "GameNum6": 0,
      "ScoreType6": "0",
      "Score6": 0,
      "SeriesTotal": 283,
      "HandicapSeriesTotal": 413,
      "PlusMinusAverage": -6,
      "TeamNum": 12
    },
    {
      "BowlerID": 59,
      "BowlerName": "Lawless, Brian",
      "TeamID": 6,
      "TeamName": "Spare Me",
      "AverageBeforeBowling": 165,
      "HandicapBeforeBowling": 49,
      "GameNum1": 1,
      "ScoreType1": "S",
      "Score1": 159,
      "GameNum2": 2,
      "ScoreType2": "S",
      "Score2": 149,
      "GameNum3": 0,
      "ScoreType3": "0",
      "Score3": 0,
      "GameNum4": 0,
      "ScoreType4": "0",
      "Score4": 0,
      "GameNum5": 0,
      "ScoreType5": "0",
      "Score5": 0,
      "GameNum6": 0,
      "ScoreType6": "0",
      "Score6": 0,
      "SeriesTotal": 308,
      "HandicapSeriesTotal": 406,
      "PlusMinusAverage": -11,
      "TeamNum": 6
    },
    {
      "BowlerID": 35,
      "BowlerName": "M, K",
      "TeamID": 21,
      "TeamName": "AWACS ON/OFF",
      "AverageBeforeBowling": 152,
      "HandicapBeforeBowling": 61,
      "GameNum1": 1,
      "ScoreType1": "S",
      "Score1": 123,
      "GameNum2": 2,
      "ScoreType2": "S",
      "Score2": 167,
      "GameNum3": 0,
      "ScoreType3": "0",
      "Score3": 0,
      "GameNum4": 0,
      "ScoreType4": "0",
      "Score4": 0,
      "GameNum5": 0,
      "ScoreType5": "0",
      "Score5": 0,
      "GameNum6": 0,
      "ScoreType6": "0",
      "Score6": 0,
      "SeriesTotal": 290,
      "HandicapSeriesTotal": 412,
      "PlusMinusAverage": -7,
      "TeamNum": 21
    },
    {
      "BowlerID": 70,
      "BowlerName": "Mcdowell, Michael",
      "TeamID": 18,
      "TeamName": "Sandbaggers",
      "AverageBeforeBowling": 195,
      "HandicapBeforeBowling": 22,
      "GameNum1": 1,
      "ScoreType1": "S",
      "Score1": 199,
      "GameNum2": 2,
      "ScoreType2": "S",
      "Score2": 186,
      "GameNum3": 0,
      "ScoreType3": "0",
      "Score3": 0,
      "GameNum4": 0,
      "ScoreType4": "0",
      "Score4": 0,
      "GameNum5": 0,
      "ScoreType5": "0",
      "Score5": 0,
      "GameNum6": 0,
      "ScoreType6": "0",
      "Score6": 0,
      "SeriesTotal": 385,
      "HandicapSeriesTotal": 429,
      "PlusMinusAverage": -3,
      "TeamNum": 18
    },
    {
      "BowlerID": 60,
      "BowlerName": "Mitchell, Melissa",
      "TeamID": 6,
      "TeamName": "Spare Me",
      "AverageBeforeBowling": 145,
      "HandicapBeforeBowling": 67,
      "GameNum1": 1,
      "ScoreType1": "S",
      "Score1": 146,
      "GameNum2": 2,
      "ScoreType2": "S",
      "Score2": 148,
      "GameNum3": 0,
      "ScoreType3": "0",
      "Score3": 0,
      "GameNum4": 0,
      "ScoreType4": "0",
      "Score4": 0,
      "GameNum5": 0,
      "ScoreType5": "0",
      "Score5": 0,
      "GameNum6": 0,
      "ScoreType6": "0",
      "Score6": 0,
      "SeriesTotal": 294,
      "HandicapSeriesTotal": 428,
      "PlusMinusAverage": 2,
      "TeamNum": 6
    },
    {
      "BowlerID": 20,
      "BowlerName": "Moffat, Andrew",
      "TeamID": 17,
      "TeamName": "Roll Clones",
      "AverageBeforeBowling": 178,
      "HandicapBeforeBowling": 37,
      "GameNum1": 1,
      "ScoreType1": "S",
      "Score1": 135,
      "GameNum2": 2,
      "ScoreType2": "S",
      "Score2": 207,
      "GameNum3": 0,
      "ScoreType3": "0",
      "Score3": 0,
      "GameNum4": 0,
      "ScoreType4": "0",
      "Score4": 0,
      "GameNum5": 0,
      "ScoreType5": "0",
      "Score5": 0,
      "GameNum6": 0,
      "ScoreType6": "0",
      "Score6": 0,
      "SeriesTotal": 342,
      "HandicapSeriesTotal": 416,
      "PlusMinusAverage": -7,
      "TeamNum": 17
    },
    {
      "BowlerID": 13,
      "BowlerName": "Nance, Katie",
      "TeamID": 15,
      "TeamName": "XXX Dancers",
      "AverageBeforeBowling": 137,
      "HandicapBeforeBowling": 74,
      "GameNum1": 1,
      "ScoreType1": "S",
      "Score1": 144,
      "GameNum2": 2,
      "ScoreType2": "S",
      "Score2": 174,
      "GameNum3": 0,
      "ScoreType3": "0",
      "Score3": 0,
      "GameNum4": 0,
      "ScoreType4": "0",
      "Score4": 0,
      "GameNum5": 0,
      "ScoreType5": "0",
      "Score5": 0,
      "GameNum6": 0,
      "ScoreType6": "0",
      "Score6": 0,
      "SeriesTotal": 318,
      "HandicapSeriesTotal": 466,
      "PlusMinusAverage": 22,
      "TeamNum": 15
    },
    {
      "BowlerID": 4,
      "BowlerName": "O, M",
      "TeamID": 20,
      "TeamName": "SPAM",
      "AverageBeforeBowling": 207,
      "HandicapBeforeBowling": 11,
      "GameNum1": 1,
      "ScoreType1": "S",
      "Score1": 245,
      "GameNum2": 2,
      "ScoreType2": "S",
      "Score2": 192,
      "GameNum3": 0,
      "ScoreType3": "0",
      "Score3": 0,
      "GameNum4": 0,
      "ScoreType4": "0",
      "Score4": 0,
      "GameNum5": 0,
      "ScoreType5": "0",
      "Score5": 0,
      "GameNum6": 0,
      "ScoreType6": "0",
      "Score6": 0,
      "SeriesTotal": 437,
      "HandicapSeriesTotal": 459,
      "PlusMinusAverage": 11,
      "TeamNum": 20
    },
    {
      "BowlerID": 23,
      "BowlerName": "Ramstead, Nick",
      "TeamID": 5,
      "TeamName": "Barely Bowling",
      "AverageBeforeBowling": 139,
      "HandicapBeforeBowling": 72,
      "GameNum1": 1,
      "ScoreType1": "S",
      "Score1": 149,
      "GameNum2": 2,
      "ScoreType2": "S",
      "Score2": 144,
      "GameNum3": 0,
      "ScoreType3": "0",
      "Score3": 0,
      "GameNum4": 0,
      "ScoreType4": "0",
      "Score4": 0,
      "GameNum5": 0,
      "ScoreType5": "0",
      "Score5": 0,
      "GameNum6": 0,
      "ScoreType6": "0",
      "Score6": 0,
      "SeriesTotal": 293,
      "HandicapSeriesTotal": 437,
      "PlusMinusAverage": 7,
      "TeamNum": 5
    },
    {
      "BowlerID": 92,
      "BowlerName": "Reed, Scot",
      "TeamID": 4,
      "TeamName": "Bad Attitude",
      "AverageBeforeBowling": 207,
      "HandicapBeforeBowling": 11,
      "GameNum1": 1,
      "ScoreType1": "S",
      "Score1": 219,
      "GameNum2": 2,
      "ScoreType2": "S",
      "Score2": 177,
      "GameNum3": 0,
      "ScoreType3": "0",
      "Score3": 0,
      "GameNum4": 0,
      "ScoreType4": "0",
      "Score4": 0,
      "GameNum5": 0,
      "ScoreType5": "0",
      "Score5": 0,
      "GameNum6": 0,
      "ScoreType6": "0",
      "Score6": 0,
      "SeriesTotal": 396,
      "HandicapSeriesTotal": 418,
      "PlusMinusAverage": -9,
      "TeamNum": 4
    },
    {
      "BowlerID": 130,
      "BowlerName": "Rhein, Bradley",
      "TeamID": 27,
      "TeamName": "The Century Club",
      "AverageBeforeBowling": 142,
      "HandicapBeforeBowling": 70,
      "GameNum1": 1,
      "ScoreType1": "S",
      "Score1": 147,
      "GameNum2": 2,
      "ScoreType2": "S",
      "Score2": 150,
      "GameNum3": 0,
      "ScoreType3": "0",
      "Score3": 0,
      "GameNum4": 0,
      "ScoreType4": "0",
      "Score4": 0,
      "GameNum5": 0,
      "ScoreType5": "0",
      "Score5": 0,
      "GameNum6": 0,
      "ScoreType6": "0",
      "Score6": 0,
      "SeriesTotal": 297,
      "HandicapSeriesTotal": 437,
      "PlusMinusAverage": 6,
      "TeamNum": 27
    },
    {
      "BowlerID": 18,
      "BowlerName": "Roggow, Brad",
      "TeamID": 24,
      "TeamName": "Mark it Zero !",
      "AverageBeforeBowling": 134,
      "HandicapBeforeBowling": 77,
      "GameNum1": 1,
      "ScoreType1": "S",
      "Score1": 136,
      "GameNum2": 2,
      "ScoreType2": "S",
      "Score2": 120,
      "GameNum3": 0,
      "ScoreType3": "0",
      "Score3": 0,
      "GameNum4": 0,
      "ScoreType4": "0",
      "Score4": 0,
      "GameNum5": 0,
      "ScoreType5": "0",
      "Score5": 0,
      "GameNum6": 0,
      "ScoreType6": "0",
      "Score6": 0,
      "SeriesTotal": 256,
      "HandicapSeriesTotal": 410,
      "PlusMinusAverage": -6,
      "TeamNum": 24
    },
    {
      "BowlerID": 97,
      "BowlerName": "Roggow, Dan",
      "TeamID": 14,
      "TeamName": "Rick Rollers",
      "AverageBeforeBowling": 135,
      "HandicapBeforeBowling": 76,
      "GameNum1": 1,
      "ScoreType1": "S",
      "Score1": 112,
      "GameNum2": 2,
      "ScoreType2": "S",
      "Score2": 112,
      "GameNum3": 0,
      "ScoreType3": "0",
      "Score3": 0,
      "GameNum4": 0,
      "ScoreType4": "0",
      "Score4": 0,
      "GameNum5": 0,
      "ScoreType5": "0",
      "Score5": 0,
      "GameNum6": 0,
      "ScoreType6": "0",
      "Score6": 0,
      "SeriesTotal": 224,
      "HandicapSeriesTotal": 376,
      "PlusMinusAverage": -23,
      "TeamNum": 14
    },
    {
      "BowlerID": 14,
      "BowlerName": "Schlichtemeier, Isaac",
      "TeamID": 19,
      "TeamName": "TB Inc LLC",
      "AverageBeforeBowling": 136,
      "HandicapBeforeBowling": 75,
      "GameNum1": 1,
      "ScoreType1": "S",
      "Score1": 178,
      "GameNum2": 2,
      "ScoreType2": "S",
      "Score2": 136,
      "GameNum3": 0,
      "ScoreType3": "0",
      "Score3": 0,
      "GameNum4": 0,
      "ScoreType4": "0",
      "Score4": 0,
      "GameNum5": 0,
      "ScoreType5": "0",
      "Score5": 0,
      "GameNum6": 0,
      "ScoreType6": "0",
      "Score6": 0,
      "SeriesTotal": 314,
      "HandicapSeriesTotal": 464,
      "PlusMinusAverage": 21,
      "TeamNum": 19
    },
    {
      "BowlerID": 48,
      "BowlerName": "Schmidt, Derek",
      "TeamID": 22,
      "TeamName": "We Don't Give A Split",
      "AverageBeforeBowling": 159,
      "HandicapBeforeBowling": 54,
      "GameNum1": 1,
      "ScoreType1": "S",
      "Score1": 188,
      "GameNum2": 2,
      "ScoreType2": "S",
      "Score2": 114,
      "GameNum3": 0,
      "ScoreType3": "0",
      "Score3": 0,
      "GameNum4": 0,
      "ScoreType4": "0",
      "Score4": 0,
      "GameNum5": 0,
      "ScoreType5": "0",
      "Score5": 0,
      "GameNum6": 0,
      "ScoreType6": "0",
      "Score6": 0,
      "SeriesTotal": 302,
      "HandicapSeriesTotal": 410,
      "PlusMinusAverage": -8,
      "TeamNum": 22
    },
    {
      "BowlerID": 50,
      "BowlerName": "Smith, Debbie",
      "TeamID": 2,
      "TeamName": "Alias Smith and Godfrey",
      "AverageBeforeBowling": 134,
      "HandicapBeforeBowling": 77,
      "GameNum1": 1,
      "ScoreType1": "S",
      "Score1": 121,
      "GameNum2": 2,
      "ScoreType2": "S",
      "Score2": 156,
      "GameNum3": 0,
      "ScoreType3": "0",
      "Score3": 0,
      "GameNum4": 0,
      "ScoreType4": "0",
      "Score4": 0,
      "GameNum5": 0,
      "ScoreType5": "0",
      "Score5": 0,
      "GameNum6": 0,
      "ScoreType6": "0",
      "Score6": 0,
      "SeriesTotal": 277,
      "HandicapSeriesTotal": 431,
      "PlusMinusAverage": 4,
      "TeamNum": 2
    },
    {
      "BowlerID": 52,
      "BowlerName": "Smith, Perry",
      "TeamID": 3,
      "TeamName": "Backstabbers",
      "AverageBeforeBowling": 190,
      "HandicapBeforeBowling": 27,
      "GameNum1": 1,
      "ScoreType1": "S",
      "Score1": 258,
      "GameNum2": 2,
      "ScoreType2": "S",
      "Score2": 199,
      "GameNum3": 0,
      "ScoreType3": "0",
      "Score3": 0,
      "GameNum4": 0,
      "ScoreType4": "0",
      "Score4": 0,
      "GameNum5": 0,
      "ScoreType5": "0",
      "Score5": 0,
      "GameNum6": 0,
      "ScoreType6": "0",
      "Score6": 0,
      "SeriesTotal": 457,
      "HandicapSeriesTotal": 511,
      "PlusMinusAverage": 38,
      "TeamNum": 3
    },
    {
      "BowlerID": 53,
      "BowlerName": "Smith, Brian",
      "TeamID": 12,
      "TeamName": "I am Root",
      "AverageBeforeBowling": 167,
      "HandicapBeforeBowling": 47,
      "GameNum1": 1,
      "ScoreType1": "S",
      "Score1": 192,
      "GameNum2": 2,
      "ScoreType2": "S",
      "Score2": 129,
      "GameNum3": 0,
      "ScoreType3": "0",
      "Score3": 0,
      "GameNum4": 0,
      "ScoreType4": "0",
      "Score4": 0,
      "GameNum5": 0,
      "ScoreType5": "0",
      "Score5": 0,
      "GameNum6": 0,
      "ScoreType6": "0",
      "Score6": 0,
      "SeriesTotal": 321,
      "HandicapSeriesTotal": 415,
      "PlusMinusAverage": -7,
      "TeamNum": 12
    },
    {
      "BowlerID": 17,
      "BowlerName": "Smith, Stan",
      "TeamID": 23,
      "TeamName": "Split Happens",
      "AverageBeforeBowling": 155,
      "HandicapBeforeBowling": 58,
      "GameNum1": 1,
      "ScoreType1": "S",
      "Score1": 133,
      "GameNum2": 2,
      "ScoreType2": "S",
      "Score2": 132,
      "GameNum3": 0,
      "ScoreType3": "0",
      "Score3": 0,
      "GameNum4": 0,
      "ScoreType4": "0",
      "Score4": 0,
      "GameNum5": 0,
      "ScoreType5": "0",
      "Score5": 0,
      "GameNum6": 0,
      "ScoreType6": "0",
      "Score6": 0,
      "SeriesTotal": 265,
      "HandicapSeriesTotal": 381,
      "PlusMinusAverage": -23,
      "TeamNum": 23
    },
    {
      "BowlerID": 176,
      "BowlerName": "S, K",
      "TeamID": 7,
      "TeamName": "Craptastic",
      "AverageBeforeBowling": 174,
      "HandicapBeforeBowling": 41,
      "GameNum1": 1,
      "ScoreType1": "S",
      "Score1": 223,
      "GameNum2": 2,
      "ScoreType2": "S",
      "Score2": 153,
      "GameNum3": 0,
      "ScoreType3": "0",
      "Score3": 0,
      "GameNum4": 0,
      "ScoreType4": "0",
      "Score4": 0,
      "GameNum5": 0,
      "ScoreType5": "0",
      "Score5": 0,
      "GameNum6": 0,
      "ScoreType6": "0",
      "Score6": 0,
      "SeriesTotal": 376,
      "HandicapSeriesTotal": 458,
      "PlusMinusAverage": 14,
      "TeamNum": 7
    },
    {
      "BowlerID": 134,
      "BowlerName": "Somers, Clifton",
      "TeamID": 25,
      "TeamName": "The Outsiders",
      "AverageBeforeBowling": 189,
      "HandicapBeforeBowling": 27,
      "GameNum1": 1,
      "ScoreType1": "S",
      "Score1": 181,
      "GameNum2": 2,
      "ScoreType2": "S",
      "Score2": 209,
      "GameNum3": 0,
      "ScoreType3": "0",
      "Score3": 0,
      "GameNum4": 0,
      "ScoreType4": "0",
      "Score4": 0,
      "GameNum5": 0,
      "ScoreType5": "0",
      "Score5": 0,
      "GameNum6": 0,
      "ScoreType6": "0",
      "Score6": 0,
      "SeriesTotal": 390,
      "HandicapSeriesTotal": 444,
      "PlusMinusAverage": 6,
      "TeamNum": 25
    },
    {
      "BowlerID": 2,
      "BowlerName": "Spencer, Andy",
      "TeamID": 8,
      "TeamName": "Lunch Hour Hookers",
      "AverageBeforeBowling": 164,
      "HandicapBeforeBowling": 50,
      "GameNum1": 1,
      "ScoreType1": "S",
      "Score1": 187,
      "GameNum2": 2,
      "ScoreType2": "S",
      "Score2": 194,
      "GameNum3": 0,
      "ScoreType3": "0",
      "Score3": 0,
      "GameNum4": 0,
      "ScoreType4": "0",
      "Score4": 0,
      "GameNum5": 0,
      "ScoreType5": "0",
      "Score5": 0,
      "GameNum6": 0,
      "ScoreType6": "0",
      "Score6": 0,
      "SeriesTotal": 381,
      "HandicapSeriesTotal": 481,
      "PlusMinusAverage": 26,
      "TeamNum": 8
    },
    {
      "BowlerID": 64,
      "BowlerName": "Spiess, Gary",
      "TeamID": 3,
      "TeamName": "Backstabbers",
      "AverageBeforeBowling": 160,
      "HandicapBeforeBowling": 54,
      "GameNum1": 1,
      "ScoreType1": "S",
      "Score1": 151,
      "GameNum2": 2,
      "ScoreType2": "S",
      "Score2": 163,
      "GameNum3": 0,
      "ScoreType3": "0",
      "Score3": 0,
      "GameNum4": 0,
      "ScoreType4": "0",
      "Score4": 0,
      "GameNum5": 0,
      "ScoreType5": "0",
      "Score5": 0,
      "GameNum6": 0,
      "ScoreType6": "0",
      "Score6": 0,
      "SeriesTotal": 314,
      "HandicapSeriesTotal": 422,
      "PlusMinusAverage": -3,
      "TeamNum": 3
    },
    {
      "BowlerID": 98,
      "BowlerName": "Tew, Ryan",
      "TeamID": 25,
      "TeamName": "The Outsiders",
      "AverageBeforeBowling": 204,
      "HandicapBeforeBowling": 14,
      "GameNum1": 1,
      "ScoreType1": "S",
      "Score1": 223,
      "GameNum2": 2,
      "ScoreType2": "S",
      "Score2": 194,
      "GameNum3": 0,
      "ScoreType3": "0",
      "Score3": 0,
      "GameNum4": 0,
      "ScoreType4": "0",
      "Score4": 0,
      "GameNum5": 0,
      "ScoreType5": "0",
      "Score5": 0,
      "GameNum6": 0,
      "ScoreType6": "0",
      "Score6": 0,
      "SeriesTotal": 417,
      "HandicapSeriesTotal": 445,
      "PlusMinusAverage": 4,
      "TeamNum": 25
    },
    {
      "BowlerID": 58,
      "BowlerName": "Thielen, Andy",
      "TeamID": 7,
      "TeamName": "Craptastic",
      "AverageBeforeBowling": 174,
      "HandicapBeforeBowling": 41,
      "GameNum1": 1,
      "ScoreType1": "S",
      "Score1": 145,
      "GameNum2": 2,
      "ScoreType2": "S",
      "Score2": 209,
      "GameNum3": 0,
      "ScoreType3": "0",
      "Score3": 0,
      "GameNum4": 0,
      "ScoreType4": "0",
      "Score4": 0,
      "GameNum5": 0,
      "ScoreType5": "0",
      "Score5": 0,
      "GameNum6": 0,
      "ScoreType6": "0",
      "Score6": 0,
      "SeriesTotal": 354,
      "HandicapSeriesTotal": 436,
      "PlusMinusAverage": 3,
      "TeamNum": 7
    },
    {
      "BowlerID": 22,
      "BowlerName": "Toothaker, James",
      "TeamID": 28,
      "TeamName": "Who gives a split",
      "AverageBeforeBowling": 149,
      "HandicapBeforeBowling": 63,
      "GameNum1": 1,
      "ScoreType1": "S",
      "Score1": 164,
      "GameNum2": 2,
      "ScoreType2": "S",
      "Score2": 181,
      "GameNum3": 0,
      "ScoreType3": "0",
      "Score3": 0,
      "GameNum4": 0,
      "ScoreType4": "0",
      "Score4": 0,
      "GameNum5": 0,
      "ScoreType5": "0",
      "Score5": 0,
      "GameNum6": 0,
      "ScoreType6": "0",
      "Score6": 0,
      "SeriesTotal": 345,
      "HandicapSeriesTotal": 471,
      "PlusMinusAverage": 23,
      "TeamNum": 28
    },
    {
      "BowlerID": 15,
      "BowlerName": "V, S",
      "TeamID": 10,
      "TeamName": "Engineering Strikes",
      "AverageBeforeBowling": 186,
      "HandicapBeforeBowling": 30,
      "GameNum1": 1,
      "ScoreType1": "S",
      "Score1": 199,
      "GameNum2": 2,
      "ScoreType2": "S",
      "Score2": 159,
      "GameNum3": 0,
      "ScoreType3": "0",
      "Score3": 0,
      "GameNum4": 0,
      "ScoreType4": "0",
      "Score4": 0,
      "GameNum5": 0,
      "ScoreType5": "0",
      "Score5": 0,
      "GameNum6": 0,
      "ScoreType6": "0",
      "Score6": 0,
      "SeriesTotal": 358,
      "HandicapSeriesTotal": 418,
      "PlusMinusAverage": -7,
      "TeamNum": 10
    },
    {
      "BowlerID": 129,
      "BowlerName": "Webster, Chance",
      "TeamID": 17,
      "TeamName": "Roll Clones",
      "AverageBeforeBowling": 168,
      "HandicapBeforeBowling": 46,
      "GameNum1": 1,
      "ScoreType1": "S",
      "Score1": 195,
      "GameNum2": 2,
      "ScoreType2": "S",
      "Score2": 205,
      "GameNum3": 0,
      "ScoreType3": "0",
      "Score3": 0,
      "GameNum4": 0,
      "ScoreType4": "0",
      "Score4": 0,
      "GameNum5": 0,
      "ScoreType5": "0",
      "Score5": 0,
      "GameNum6": 0,
      "ScoreType6": "0",
      "Score6": 0,
      "SeriesTotal": 400,
      "HandicapSeriesTotal": 492,
      "PlusMinusAverage": 32,
      "TeamNum": 17
    },
    {
      "BowlerID": 128,
      "BowlerName": "W, C",
      "TeamID": 19,
      "TeamName": "TB Inc LLC",
      "AverageBeforeBowling": 164,
      "HandicapBeforeBowling": 50,
      "GameNum1": 1,
      "ScoreType1": "S",
      "Score1": 160,
      "GameNum2": 2,
      "ScoreType2": "S",
      "Score2": 183,
      "GameNum3": 0,
      "ScoreType3": "0",
      "Score3": 0,
      "GameNum4": 0,
      "ScoreType4": "0",
      "Score4": 0,
      "GameNum5": 0,
      "ScoreType5": "0",
      "Score5": 0,
      "GameNum6": 0,
      "ScoreType6": "0",
      "Score6": 0,
      "SeriesTotal": 343,
      "HandicapSeriesTotal": 443,
      "PlusMinusAverage": 7,
      "TeamNum": 19
    },
    {
      "BowlerID": 116,
      "BowlerName": "W, D",
      "TeamID": 14,
      "TeamName": "Rick Rollers",
      "AverageBeforeBowling": 150,
      "HandicapBeforeBowling": 63,
      "GameNum1": 1,
      "ScoreType1": "S",
      "Score1": 126,
      "GameNum2": 2,
      "ScoreType2": "S",
      "Score2": 108,
      "GameNum3": 0,
      "ScoreType3": "0",
      "Score3": 0,
      "GameNum4": 0,
      "ScoreType4": "0",
      "Score4": 0,
      "GameNum5": 0,
      "ScoreType5": "0",
      "Score5": 0,
      "GameNum6": 0,
      "ScoreType6": "0",
      "Score6": 0,
      "SeriesTotal": 234,
      "HandicapSeriesTotal": 360,
      "PlusMinusAverage": -33,
      "TeamNum": 14
    },
    {
      "BowlerID": 72,
      "BowlerName": "Yost, Henry",
      "TeamID": 18,
      "TeamName": "Sandbaggers",
      "AverageBeforeBowling": 168,
      "HandicapBeforeBowling": 46,
      "GameNum1": 1,
      "ScoreType1": "S",
      "Score1": 178,
      "GameNum2": 2,
      "ScoreType2": "S",
      "Score2": 199,
      "GameNum3": 0,
      "ScoreType3": "0",
      "Score3": 0,
      "GameNum4": 0,
      "ScoreType4": "0",
      "Score4": 0,
      "GameNum5": 0,
      "ScoreType5": "0",
      "Score5": 0,
      "GameNum6": 0,
      "ScoreType6": "0",
      "Score6": 0,
      "SeriesTotal": 377,
      "HandicapSeriesTotal": 469,
      "PlusMinusAverage": 20,
      "TeamNum": 18
    }
  ],
  "Total": 56,
  "AggregateResults": null,
  "Errors": null
}